llama_index/graph_stores/falkordb/__init__.py
llama_index/graph_stores/falkordb/base.py
llama_index/graph_stores/falkordb/falkordb_property_graph.py
llama_index_graph_stores_falkordb-0.4.1.dist-info/METADATA
llama_index_graph_stores_falkordb-0.4.1.dist-info/WHEEL
llama_index_graph_stores_falkordb-0.4.1.dist-info/licenses/LICENSE
llama_index_graph_stores_falkordb-0.4.1.dist-info/RECORD
