Metadata-Version: 2.4
Name: llama-index-graph-stores-falkordb
Version: 0.4.1
Summary: llama-index graph stores falkordb integration
Author-email: Your Name <you@example.com>
License-Expression: MIT
License-File: LICENSE
Requires-Python: <4.0,>=3.9
Requires-Dist: falkordb<2,>=1.0.8
Requires-Dist: llama-index-core<0.15,>=0.13.0
